MANIFEST.in
README.rst
setup.py
django_viewform.egg-info/PKG-INFO
django_viewform.egg-info/SOURCES.txt
django_viewform.egg-info/dependency_links.txt
django_viewform.egg-info/not-zip-safe
django_viewform.egg-info/requires.txt
django_viewform.egg-info/top_level.txt
viewform/__init__.py
viewform/base.py
viewform/static/viewform/bootstrap3/viewform.css
viewform/static/viewform/bootstrap3/bootstrap-switch/bootstrap-switch.css
viewform/static/viewform/bootstrap3/bootstrap-switch/bootstrap-switch.js
viewform/static/viewform/bootstrap3/bootstrap/css/bootstrap-theme.css
viewform/static/viewform/bootstrap3/bootstrap/css/bootstrap-theme.min.css
viewform/static/viewform/bootstrap3/bootstrap/css/bootstrap.css
viewform/static/viewform/bootstrap3/bootstrap/css/bootstrap.min.css
viewform/static/viewform/bootstrap3/bootstrap/fonts/glyphicons-halflings-regular.eot
viewform/static/viewform/bootstrap3/bootstrap/fonts/glyphicons-halflings-regular.svg
viewform/static/viewform/bootstrap3/bootstrap/fonts/glyphicons-halflings-regular.ttf
viewform/static/viewform/bootstrap3/bootstrap/fonts/glyphicons-halflings-regular.woff
viewform/static/viewform/bootstrap3/bootstrap/js/bootstrap.js
viewform/static/viewform/bootstrap3/bootstrap/js/bootstrap.min.js
viewform/static/viewform/bootstrap3/chosen/chosen-sprite.png
viewform/static/viewform/bootstrap3/chosen/chosen-sprite@2x.png
viewform/static/viewform/bootstrap3/chosen/chosen.jquery.min.js
viewform/static/viewform/bootstrap3/chosen/chosen.min.css
viewform/static/viewform/bootstrap3/datetimepicker/bootstrap-datetimepicker.min.css
viewform/static/viewform/bootstrap3/datetimepicker/bootstrap-datetimepicker.min.js
viewform/static/viewform/bootstrap3/datetimepicker/locales/bootstrap-datetimepicker.ar.js
viewform/static/viewform/bootstrap3/datetimepicker/locales/bootstrap-datetimepicker.bg.js
viewform/static/viewform/bootstrap3/datetimepicker/locales/bootstrap-datetimepicker.ca.js
viewform/static/viewform/bootstrap3/datetimepicker/locales/bootstrap-datetimepicker.cs.js
viewform/static/viewform/bootstrap3/datetimepicker/locales/bootstrap-datetimepicker.da.js
viewform/static/viewform/bootstrap3/datetimepicker/locales/bootstrap-datetimepicker.de.js
