Metadata-Version: 1.1
Name: django-viewform
Version: 0.1.0
Summary: Template driven form rendering for django.
Home-page: http://github.com/viewflow/viewform
Author: Mikhail Podgurskiy
Author-email: kmmbvnr@gmail.com
License: LGPLv3
Keywords: django
Platform: any
Classifier: Development Status :: 3 - Alpha
Classifier: Environment :: Web Environment
Classifier: Intended Audience :: Developers
Classifier: License :: OSI Approved :: MIT License
Classifier: Operating System :: OS Independent
Classifier: Programming Language :: Python
Classifier: Programming Language :: Python :: 3
Classifier: Framework :: Django
